gensaschema/__init__.py
gensaschema/_column.py
gensaschema/_config.py
gensaschema/_constraint.py
gensaschema/_exceptions.py
gensaschema/_meta.py
gensaschema/_schema.py
gensaschema/_symbols.py
gensaschema/_table.py
gensaschema/_template.py
gensaschema/_type.py
gensaschema/_util.py
gensaschema/constraints.py
gensaschema-0.6.10.dist-info/licenses/LICENSE
gensaschema-0.6.10.dist-info/METADATA
gensaschema-0.6.10.dist-info/WHEEL
gensaschema-0.6.10.dist-info/top_level.txt
gensaschema-0.6.10.dist-info/RECORD
